README.rst
setup.py
scotch/__init__.py
scotch/app.py
scotch/cmd.py
scotch.egg-info/PKG-INFO
scotch.egg-info/SOURCES.txt
scotch.egg-info/dependency_links.txt
scotch.egg-info/entry_points.txt
scotch.egg-info/requires.txt
scotch.egg-info/top_level.txt
scotch/plugins/__init__.py
scotch/plugins/git/__init__.py
scotch/plugins/nginx/__init__.py
scotch/plugins/uwsgi/__init__.py