Metadata-Version: 1.0
Name: scotch
Version: 0.3
Summary: Simplifies WSGI application deployment.
Home-page: http://github.com/mbr/scotch
Author: Marc Brinkmann
Author-email: git@marcbrinkmann.de
License: MIT
Platform: UNKNOWN
